reminder/__init__.py
status_reminder-0.0.3.dist-info/LICENSE
status_reminder-0.0.3.dist-info/METADATA
status_reminder-0.0.3.dist-info/WHEEL
status_reminder-0.0.3.dist-info/top_level.txt
status_reminder-0.0.3.dist-info/RECORD
